{
  "run_id": "39b1296f-91d9-456e-b318-afe2b67baa49",
  "saved_at": "2025-09-29T08:42:25.843Z",
  "epics": [
    {
      "id": "EPIC-1",
      "title": "User Registration and Authentication",
      "description": "Enable secure customer account creation, login, and management to allow personalized appointment booking and management. This is foundational for tracking user activity and providing a seamless, secure experience.",
      "assignee": "712020:06da9bb0-aef1-4524-89c8-418636a8f4cb",
      "assignee_name": "Saran K",
      "stories": [
        {
          "id": "FE-1",
          "title": "Customer Registration UI",
          "description": "As a new customer, I want to register for an account via web and mobile so that I can book and manage appointments.",
          "assignee": "712020:b24d82dc-9137-4e86-839d-135987b9d377",
          "assignee_name": "arun",
          "subtasks": [
            {
              "id": "FE-1-1",
              "title": "Design Registration Form",
              "description": "Create responsive registration form UI for web and mobile.",
              "assignee": "712020:603329f9-a8bc-4cc2-831c-968d1bcda7f4",
              "assignee_name": "anirudh"
            },
            {
              "id": "FE-1-2",
              "title": "Implement Form Validation",
              "description": "Add client-side validation for required fields and password strength.",
              "assignee": "712020:b24d82dc-9137-4e86-839d-135987b9d377",
              "assignee_name": "arun"
            },
            {
              "id": "FE-1-3",
              "title": "Integrate with Backend API",
              "description": "Connect registration form to backend registration endpoint.",
              "assignee": "712020:603329f9-a8bc-4cc2-831c-968d1bcda7f4",
              "assignee_name": "anirudh"
            }
          ]
        },
        {
          "id": "BE-1",
          "title": "User Registration API",
          "description": "As a backend developer, I want to provide secure endpoints for user registration and store user data securely.",
          "assignee": "712020:451a761b-476d-44f8-a28f-4bf642917348",
          "assignee_name": "sivaseelan",
          "subtasks": [
            {
              "id": "BE-1-1",
              "title": "Create Registration Endpoint",
              "description": "Develop REST API endpoint for user registration.",
              "assignee": "712020:6ef43350-55eb-49ad-aeaf-cb9807f21dd0",
              "assignee_name": "naveen"
            },
            {
              "id": "BE-1-2",
              "title": "Implement Password Hashing",
              "description": "Hash passwords using industry best practices (e.g., bcrypt).",
              "assignee": "712020:451a761b-476d-44f8-a28f-4bf642917348",
              "assignee_name": "sivaseelan"
            },
            {
              "id": "BE-1-3",
              "title": "Validate Unique Email",
              "description": "Ensure email uniqueness in the database.",
              "assignee": "712020:6ef43350-55eb-49ad-aeaf-cb9807f21dd0",
              "assignee_name": "naveen"
            },
            {
              "id": "BE-1-4",
              "title": "Return API Responses",
              "description": "Return success or error messages as appropriate.",
              "assignee": "712020:451a761b-476d-44f8-a28f-4bf642917348",
              "assignee_name": "sivaseelan"
            }
          ]
        },
        {
          "id": "FE-2",
          "title": "Customer Login UI",
          "description": "As a registered customer, I want to log in securely to access my account and manage appointments.",
          "assignee": "712020:b24d82dc-9137-4e86-839d-135987b9d377",
          "assignee_name": "arun",
          "subtasks": [
            {
              "id": "FE-2-1",
              "title": "Design Login Form",
              "description": "Create responsive login form UI for web and mobile.",
              "assignee": "712020:603329f9-a8bc-4cc2-831c-968d1bcda7f4",
              "assignee_name": "anirudh"
            },
            {
              "id": "FE-2-2",
              "title": "Implement Form Validation",
              "description": "Add client-side validation for login fields.",
              "assignee": "712020:b24d82dc-9137-4e86-839d-135987b9d377",
              "assignee_name": "arun"
            },
            {
              "id": "FE-2-3",
              "title": "Integrate with Backend API",
              "description": "Connect login form to backend authentication endpoint.",
              "assignee": "712020:603329f9-a8bc-4cc2-831c-968d1bcda7f4",
              "assignee_name": "anirudh"
            }
          ]
        },
        {
          "id": "BE-2",
          "title": "User Authentication API",
          "description": "As a backend developer, I want to provide secure login and session management for users.",
          "assignee": "712020:6ef43350-55eb-49ad-aeaf-cb9807f21dd0",
          "assignee_name": "naveen",
          "subtasks": [
            {
              "id": "BE-2-1",
              "title": "Create Authentication Endpoint",
              "description": "Develop REST API endpoint for user login.",
              "assignee": "712020:451a761b-476d-44f8-a28f-4bf642917348",
              "assignee_name": "sivaseelan"
            },
            {
              "id": "BE-2-2",
              "title": "Implement JWT/Session Management",
              "description": "Issue and validate JWT tokens or manage sessions securely.",
              "assignee": "712020:6ef43350-55eb-49ad-aeaf-cb9807f21dd0",
              "assignee_name": "naveen"
            },
            {
              "id": "BE-2-3",
              "title": "Handle Authentication Errors",
              "description": "Return appropriate error messages for failed logins.",
              "assignee": "712020:451a761b-476d-44f8-a28f-4bf642917348",
              "assignee_name": "sivaseelan"
            }
          ]
        },
        {
          "id": "QA-1",
          "title": "User Registration and Authentication Testing",
          "description": "As a QA engineer, I want to verify that registration and authentication work as expected and are secure.",
          "assignee": "712020:e2598059-441e-4074-80fc-d51b8f3dc5ed",
          "assignee_name": "dhanushya",
          "subtasks": [
            {
              "id": "QA-1-1",
              "title": "Functional Testing",
              "description": "Test all registration and login scenarios.",
              "assignee": "712020:1028cd78-a3ee-4236-ab16-9fd7850f90c3",
              "assignee_name": "karthik"
            },
            {
              "id": "QA-1-2",
              "title": "Security Testing",
              "description": "Test for common security vulnerabilities.",
              "assignee": "712020:e2598059-441e-4074-80fc-d51b8f3dc5ed",
              "assignee_name": "dhanushya"
            }
          ]
        },
        {
          "id": "DEVOPS-1",
          "title": "SSL/TLS Setup",
          "description": "As a DevOps engineer, I want to ensure all user data is encrypted in transit.",
          "assignee": "712020:f3df4329-0746-45c4-ab49-dd67f1471c93",
          "assignee_name": "ashwin",
          "subtasks": [
            {
              "id": "DEVOPS-1-1",
              "title": "Obtain SSL/TLS Certificates",
              "description": "Purchase or generate SSL/TLS certificates for the domain.",
              "assignee": "712020:f3df4329-0746-45c4-ab49-dd67f1471c93",
              "assignee_name": "ashwin"
            },
            {
              "id": "DEVOPS-1-2",
              "title": "Configure Web Servers",
              "description": "Install and configure certificates on web servers.",
              "assignee": "712020:f3df4329-0746-45c4-ab49-dd67f1471c93",
              "assignee_name": "ashwin"
            },
            {
              "id": "DEVOPS-1-3",
              "title": "Enforce HTTPS",
              "description": "Redirect all HTTP traffic to HTTPS.",
              "assignee": "712020:f3df4329-0746-45c4-ab49-dd67f1471c93",
              "assignee_name": "ashwin"
            }
          ]
        }
      ]
    },
    {
      "id": "EPIC-2",
      "title": "Appointment Scheduling, Rescheduling, and Cancellation",
      "description": "Enable customers to search, book, reschedule, and cancel appointments online, reducing manual errors and administrative workload while improving customer convenience.",
      "assignee": "712020:06da9bb0-aef1-4524-89c8-418636a8f4cb",
      "assignee_name": "Saran K",
      "stories": [
        {
          "id": "FE-3",
          "title": "Appointment Booking UI",
          "description": "As a customer, I want to search for available slots and book appointments via web and mobile.",
          "assignee": "712020:b24d82dc-9137-4e86-839d-135987b9d377",
          "assignee_name": "arun",
          "subtasks": [
            {
              "id": "FE-3-1",
              "title": "Design Calendar View",
              "description": "Create a responsive calendar UI to display available slots.",
              "assignee": "712020:603329f9-a8bc-4cc2-831c-968d1bcda7f4",
              "assignee_name": "anirudh"
            },
            {
              "id": "FE-3-2",
              "title": "Implement Slot Selection",
              "description": "Allow users to select and book available slots.",
              "assignee": "712020:b24d82dc-9137-4e86-839d-135987b9d377",
              "assignee_name": "arun"
            },
            {
              "id": "FE-3-3",
              "title": "Integrate with Booking API",
              "description": "Connect UI to backend booking endpoint.",
              "assignee": "712020:603329f9-a8bc-4cc2-831c-968d1bcda7f4",
              "assignee_name": "anirudh"
            }
          ]
        },
        {
          "id": "BE-3",
          "title": "Appointment Booking API",
          "description": "As a backend developer, I want to provide endpoints for searching, booking, rescheduling, and cancelling appointments.",
          "assignee": "712020:451a761b-476d-44f8-a28f-4bf642917348",
          "assignee_name": "sivaseelan",
          "subtasks": [
            {
              "id": "BE-3-1",
              "title": "Search Slots Endpoint",
              "description": "Develop endpoint to return available appointment slots.",
              "assignee": "712020:6ef43350-55eb-49ad-aeaf-cb9807f21dd0",
              "assignee_name": "naveen"
            },
            {
              "id": "BE-3-2",
              "title": "Book Appointment Endpoint",
              "description": "Develop endpoint to book appointments and prevent double-booking.",
              "assignee": "712020:451a761b-476d-44f8-a28f-4bf642917348",
              "assignee_name": "sivaseelan"
            },
            {
              "id": "BE-3-3",
              "title": "Reschedule/Cancel Endpoint",
              "description": "Develop endpoints to reschedule or cancel appointments.",
              "assignee": "712020:6ef43350-55eb-49ad-aeaf-cb9807f21dd0",
              "assignee_name": "naveen"
            }
          ]
        },
        {
          "id": "FE-4",
          "title": "Appointment Management UI",
          "description": "As a customer, I want to view, reschedule, or cancel my appointments.",
          "assignee": "712020:603329f9-a8bc-4cc2-831c-968d1bcda7f4",
          "assignee_name": "anirudh",
          "subtasks": [
            {
              "id": "FE-4-1",
              "title": "Display Appointments List",
              "description": "Show upcoming appointments in user dashboard.",
              "assignee": "712020:b24d82dc-9137-4e86-839d-135987b9d377",
              "assignee_name": "arun"
            },
            {
              "id": "FE-4-2",
              "title": "Implement Reschedule/Cancel Actions",
              "description": "Allow users to reschedule or cancel appointments from the UI.",
              "assignee": "712020:603329f9-a8bc-4cc2-831c-968d1bcda7f4",
              "assignee_name": "anirudh"
            },
            {
              "id": "FE-4-3",
              "title": "Integrate with Backend API",
              "description": "Connect UI actions to backend endpoints.",
              "assignee": "712020:b24d82dc-9137-4e86-839d-135987b9d377",
              "assignee_name": "arun"
            }
          ]
        },
        {
          "id": "QA-2",
          "title": "Appointment Booking and Management Testing",
          "description": "As a QA engineer, I want to verify that appointment booking, rescheduling, and cancellation work as expected.",
          "assignee": "712020:1028cd78-a3ee-4236-ab16-9fd7850f90c3",
          "assignee_name": "karthik",
          "subtasks": [
            {
              "id": "QA-2-1",
              "title": "Functional Testing",
              "description": "Test all appointment management scenarios.",
              "assignee": "712020:e2598059-441e-4074-80fc-d51b8f3dc5ed",
              "assignee_name": "dhanushya"
            },
            {
              "id": "QA-2-2",
              "title": "Edge Case Testing",
              "description": "Test edge cases and error handling.",
              "assignee": "712020:1028cd78-a3ee-4236-ab16-9fd7850f90c3",
              "assignee_name": "karthik"
            }
          ]
        },
        {
          "id": "UX-1",
          "title": "User Experience Design for Booking Flow",
          "description": "As a UX designer, I want to design intuitive flows for booking, rescheduling, and cancelling appointments.",
          "assignee": "712020:b24d82dc-9137-4e86-839d-135987b9d377",
          "assignee_name": "arun",
          "subtasks": [
            {
              "id": "UX-1-1",
              "title": "Create Wireframes",
              "description": "Design wireframes for all appointment management flows.",
              "assignee": "712020:603329f9-a8bc-4cc2-831c-968d1bcda7f4",
              "assignee_name": "anirudh"
            },
            {
              "id": "UX-1-2",
              "title": "Conduct User Testing",
              "description": "Test wireframes with sample users and iterate.",
              "assignee": "712020:b24d82dc-9137-4e86-839d-135987b9d377",
              "assignee_name": "arun"
            }
          ]
        }
      ]
    },
    {
      "id": "EPIC-3",
      "title": "Automated Notifications and Reminders",
      "description": "Send automated booking confirmations and reminders via email/SMS to reduce no-shows and improve customer experience.",
      "assignee": "712020:06da9bb0-aef1-4524-89c8-418636a8f4cb",
      "assignee_name": "Saran K",
      "stories": [
        {
          "id": "BE-4",
          "title": "Notification Service Integration",
          "description": "As a backend developer, I want to integrate with email and SMS providers to send notifications.",
          "assignee": "712020:6ef43350-55eb-49ad-aeaf-cb9807f21dd0",
          "assignee_name": "naveen",
          "subtasks": [
            {
              "id": "BE-4-1",
              "title": "Integrate Email Provider",
              "description": "Connect to email service (e.g., SendGrid) for sending notifications.",
              "assignee": "712020:451a761b-476d-44f8-a28f-4bf642917348",
              "assignee_name": "sivaseelan"
            },
            {
              "id": "BE-4-2",
              "title": "Integrate SMS Provider",
              "description": "Connect to SMS service (e.g., Twilio) for sending notifications.",
              "assignee": "712020:6ef43350-55eb-49ad-aeaf-cb9807f21dd0",
              "assignee_name": "naveen"
            },
            {
              "id": "BE-4-3",
              "title": "Implement Logging for Failures",
              "description": "Log failed notification attempts for monitoring.",
              "assignee": "712020:451a761b-476d-44f8-a28f-4bf642917348",
              "assignee_name": "sivaseelan"
            }
          ]
        },
        {
          "id": "BE-5",
          "title": "Reminder Scheduler",
          "description": "As a backend developer, I want to schedule reminders to be sent 24 hours before appointments.",
          "assignee": "712020:451a761b-476d-44f8-a28f-4bf642917348",
          "assignee_name": "sivaseelan",
          "subtasks": [
            {
              "id": "BE-5-1",
              "title": "Implement Scheduler",
              "description": "Develop background job to trigger reminders.",
              "assignee": "712020:6ef43350-55eb-49ad-aeaf-cb9807f21dd0",
              "assignee_name": "naveen"
            },
            {
              "id": "BE-5-2",
              "title": "Handle Cancellations",
              "description": "Ensure reminders are not sent for cancelled appointments.",
              "assignee": "712020:451a761b-476d-44f8-a28f-4bf642917348",
              "assignee_name": "sivaseelan"
            }
          ]
        },
        {
          "id": "FE-5",
          "title": "Notification Preferences UI",
          "description": "As a customer, I want to manage my notification preferences (email/SMS).",
          "assignee": "712020:603329f9-a8bc-4cc2-831c-968d1bcda7f4",
          "assignee_name": "anirudh",
          "subtasks": [
            {
              "id": "FE-5-1",
              "title": "Design Preferences UI",
              "description": "Create UI for managing notification preferences.",
              "assignee": "712020:b24d82dc-9137-4e86-839d-135987b9d377",
              "assignee_name": "arun"
            },
            {
              "id": "FE-5-2",
              "title": "Integrate with Backend",
              "description": "Connect UI to backend to save preferences.",
              "assignee": "712020:603329f9-a8bc-4cc2-831c-968d1bcda7f4",
              "assignee_name": "anirudh"
            }
          ]
        },
        {
          "id": "QA-3",
          "title": "Notification and Reminder Testing",
          "description": "As a QA engineer, I want to verify that notifications and reminders are sent correctly.",
          "assignee": "712020:e2598059-441e-4074-80fc-d51b8f3dc5ed",
          "assignee_name": "dhanushya",
          "subtasks": [
            {
              "id": "QA-3-1",
              "title": "Functional Testing",
              "description": "Test all notification and reminder scenarios.",
              "assignee": "712020:1028cd78-a3ee-4236-ab16-9fd7850f90c3",
              "assignee_name": "karthik"
            },
            {
              "id": "QA-3-2",
              "title": "Preference Testing",
              "description": "Test opt-in/opt-out functionality.",
              "assignee": "712020:e2598059-441e-4074-80fc-d51b8f3dc5ed",
              "assignee_name": "dhanushya"
            }
          ]
        },
        {
          "id": "PM-1",
          "title": "Legal Review of Notification Content",
          "description": "As a product manager, I want to ensure all notification content complies with legal and privacy requirements.",
          "assignee": "712020:06da9bb0-aef1-4524-89c8-418636a8f4cb",
          "assignee_name": "Saran K",
          "subtasks": [
            {
              "id": "PM-1-1",
              "title": "Draft Notification Templates",
              "description": "Prepare email/SMS templates for legal review.",
              "assignee": "712020:06da9bb0-aef1-4524-89c8-418636a8f4cb",
              "assignee_name": "Saran K"
            },
            {
              "id": "PM-1-2",
              "title": "Coordinate Legal Review",
              "description": "Work with legal team to review and approve templates.",
              "assignee": "712020:73d689d5-2ee3-45a6-9a9d-e6b3bce3dcda",
              "assignee_name": "babu"
            }
          ]
        }
      ]
    },
    {
      "id": "EPIC-4",
      "title": "Admin Dashboard and Reporting",
      "description": "Provide staff with an admin dashboard to view, edit, and cancel bookings, and generate reports for business insights.",
      "assignee": "712020:06da9bb0-aef1-4524-89c8-418636a8f4cb",
      "assignee_name": "Saran K",
      "stories": [
        {
          "id": "FE-6",
          "title": "Admin Dashboard UI",
          "description": "As an admin, I want a dashboard to view and manage all bookings.",
          "assignee": "712020:603329f9-a8bc-4cc2-831c-968d1bcda7f4",
          "assignee_name": "anirudh",
          "subtasks": [
            {
              "id": "FE-6-1",
              "title": "Design Dashboard UI",
              "description": "Create responsive dashboard for admins.",
              "assignee": "712020:b24d82dc-9137-4e86-839d-135987b9d377",
              "assignee_name": "arun"
            },
            {
              "id": "FE-6-2",
              "title": "Implement Booking Management Actions",
              "description": "Enable edit and cancel actions in the dashboard.",
              "assignee": "712020:603329f9-a8bc-4cc2-831c-968d1bcda7f4",
              "assignee_name": "anirudh"
            },
            {
              "id": "FE-6-3",
              "title": "Integrate with Backend",
              "description": "Connect dashboard to backend endpoints.",
              "assignee": "712020:b24d82dc-9137-4e86-839d-135987b9d377",
              "assignee_name": "arun"
            }
          ]
        },
        {
          "id": "BE-6",
          "title": "Admin Booking Management API",
          "description": "As a backend developer, I want to provide endpoints for admins to view, edit, and cancel bookings.",
          "assignee": "712020:451a761b-476d-44f8-a28f-4bf642917348",
          "assignee_name": "sivaseelan",
          "subtasks": [
            {
              "id": "BE-6-1",
              "title": "View Bookings Endpoint",
              "description": "Develop endpoint to list all bookings for admins.",
              "assignee": "712020:6ef43350-55eb-49ad-aeaf-cb9807f21dd0",
              "assignee_name": "naveen"
            },
            {
              "id": "BE-6-2",
              "title": "Edit/Cancel Booking Endpoint",
              "description": "Develop endpoints for editing and cancelling bookings.",
              "assignee": "712020:451a761b-476d-44f8-a28f-4bf642917348",
              "assignee_name": "sivaseelan"
            },
            {
              "id": "BE-6-3",
              "title": "Admin Access Control",
              "description": "Restrict access to admin endpoints.",
              "assignee": "712020:6ef43350-55eb-49ad-aeaf-cb9807f21dd0",
              "assignee_name": "naveen"
            }
          ]
        },
        {
          "id": "FE-7",
          "title": "Reporting UI",
          "description": "As an admin, I want to view daily, weekly, and monthly reports on bookings.",
          "assignee": "712020:603329f9-a8bc-4cc2-831c-968d1bcda7f4",
          "assignee_name": "anirudh",
          "subtasks": [
            {
              "id": "FE-7-1",
              "title": "Design Reports UI",
              "description": "Create UI for displaying reports.",
              "assignee": "712020:b24d82dc-9137-4e86-839d-135987b9d377",
              "assignee_name": "arun"
            },
            {
              "id": "FE-7-2",
              "title": "Integrate with Reporting API",
              "description": "Connect UI to backend reporting endpoints.",
              "assignee": "712020:603329f9-a8bc-4cc2-831c-968d1bcda7f4",
              "assignee_name": "anirudh"
            }
          ]
        },
        {
          "id": "BE-7",
          "title": "Reporting API",
          "description": "As a backend/data engineer, I want to provide endpoints to generate daily, weekly, and monthly reports.",
          "assignee": "712020:e2598059-441e-4074-80fc-d51b8f3dc5ed",
          "assignee_name": "dhanushya",
          "subtasks": [
            {
              "id": "BE-7-1",
              "title": "Generate Reports Logic",
              "description": "Implement logic to aggregate booking data for reports.",
              "assignee": "712020:1028cd78-a3ee-4236-ab16-9fd7850f90c3",
              "assignee_name": "karthik"
            },
            {
              "id": "BE-7-2",
              "title": "Reporting Endpoints",
              "description": "Develop API endpoints for report retrieval.",
              "assignee": "712020:e2598059-441e-4074-80fc-d51b8f3dc5ed",
              "assignee_name": "dhanushya"
            }
          ]
        },
        {
          "id": "QA-4",
          "title": "Admin Dashboard and Reporting Testing",
          "description": "As a QA engineer, I want to verify that admin dashboard and reporting features work as expected.",
          "assignee": "712020:1028cd78-a3ee-4236-ab16-9fd7850f90c3",
          "assignee_name": "karthik",
          "subtasks": [
            {
              "id": "QA-4-1",
              "title": "Functional Testing",
              "description": "Test all admin dashboard actions.",
              "assignee": "712020:e2598059-441e-4074-80fc-d51b8f3dc5ed",
              "assignee_name": "dhanushya"
            },
            {
              "id": "QA-4-2",
              "title": "Report Accuracy Testing",
              "description": "Verify accuracy of generated reports.",
              "assignee": "712020:1028cd78-a3ee-4236-ab16-9fd7850f90c3",
              "assignee_name": "karthik"
            }
          ]
        },
        {
          "id": "PM-2",
          "title": "Admin Training and Documentation",
          "description": "As a product manager, I want to provide documentation and training for staff using the admin dashboard.",
          "assignee": "712020:06da9bb0-aef1-4524-89c8-418636a8f4cb",
          "assignee_name": "Saran K",
          "subtasks": [
            {
              "id": "PM-2-1",
              "title": "Create User Guides",
              "description": "Write documentation for admin dashboard features.",
              "assignee": "712020:06da9bb0-aef1-4524-89c8-418636a8f4cb",
              "assignee_name": "Saran K"
            },
            {
              "id": "PM-2-2",
              "title": "Conduct Training Sessions",
              "description": "Organize and deliver training for staff.",
              "assignee": "712020:9a0e7522-260c-427c-b390-f5027156b72b",
              "assignee_name": "sujee"
            }
          ]
        }
      ]
    },
    {
      "id": "EPIC-5",
      "title": "Infrastructure, Security, and Compliance",
      "description": "Ensure the system is secure, scalable, and compliant with technical requirements, including cloud hosting, encryption, and high availability.",
      "assignee": "712020:06da9bb0-aef1-4524-89c8-418636a8f4cb",
      "assignee_name": "Saran K",
      "stories": [
        {
          "id": "DEVOPS-2",
          "title": "Cloud Infrastructure Setup",
          "description": "As a DevOps engineer, I want to provision cloud infrastructure to host the application and database.",
          "assignee": "712020:f3df4329-0746-45c4-ab49-dd67f1471c93",
          "assignee_name": "ashwin",
          "subtasks": [
            {
              "id": "DEVOPS-2-1",
              "title": "Provision Cloud Resources",
              "description": "Set up compute, storage, and networking resources.",
              "assignee": "712020:f3df4329-0746-45c4-ab49-dd67f1471c93",
              "assignee_name": "ashwin"
            },
            {
              "id": "DEVOPS-2-2",
              "title": "Deploy Application",
              "description": "Deploy web and backend services to cloud.",
              "assignee": "712020:f3df4329-0746-45c4-ab49-dd67f1471c93",
              "assignee_name": "ashwin"
            },
            {
              "id": "DEVOPS-2-3",
              "title": "Deploy Database",
              "description": "Set up and configure cloud database.",
              "assignee": "712020:f3df4329-0746-45c4-ab49-dd67f1471c93",
              "assignee_name": "ashwin"
            }
          ]
        },
        {
          "id": "DEVOPS-3",
          "title": "Monitoring and High Availability",
          "description": "As a DevOps engineer, I want to monitor system health and ensure 99.5% uptime.",
          "assignee": "712020:f3df4329-0746-45c4-ab49-dd67f1471c93",
          "assignee_name": "ashwin",
          "subtasks": [
            {
              "id": "DEVOPS-3-1",
              "title": "Set Up Monitoring Tools",
              "description": "Install and configure monitoring (e.g., CloudWatch, Datadog).",
              "assignee": "712020:f3df4329-0746-45c4-ab49-dd67f1471c93",
              "assignee_name": "ashwin"
            },
            {
              "id": "DEVOPS-3-2",
              "title": "Configure Alerts",
              "description": "Set up alerts for system downtime or performance issues.",
              "assignee": "712020:f3df4329-0746-45c4-ab49-dd67f1471c93",
              "assignee_name": "ashwin"
            },
            {
              "id": "DEVOPS-3-3",
              "title": "Implement High Availability",
              "description": "Deploy application in multiple availability zones.",
              "assignee": "712020:f3df4329-0746-45c4-ab49-dd67f1471c93",
              "assignee_name": "ashwin"
            }
          ]
        },
        {
          "id": "SEC-1",
          "title": "Security and Compliance Review",
          "description": "As an IT/security engineer, I want to ensure the system meets security and compliance requirements.",
          "assignee": "712020:d85fee80-33e7-47e6-9060-cf1e53380d45",
          "assignee_name": "satheesh",
          "subtasks": [
            {
              "id": "SEC-1-1",
              "title": "Encrypt Data at Rest",
              "description": "Enable encryption for all stored data.",
              "assignee": "712020:d85fee80-33e7-47e6-9060-cf1e53380d45",
              "assignee_name": "satheesh"
            },
            {
              "id": "SEC-1-2",
              "title": "Conduct Vulnerability Scans",
              "description": "Run security scans on application and infrastructure.",
              "assignee": "712020:d85fee80-33e7-47e6-9060-cf1e53380d45",
              "assignee_name": "satheesh"
            },
            {
              "id": "SEC-1-3",
              "title": "Complete Compliance Checklist",
              "description": "Review and document compliance with relevant standards.",
              "assignee": "712020:d85fee80-33e7-47e6-9060-cf1e53380d45",
              "assignee_name": "satheesh"
            }
          ]
        },
        {
          "id": "QA-5",
          "title": "Performance and Load Testing",
          "description": "As a QA engineer, I want to verify the system supports at least 500 concurrent users.",
          "assignee": "712020:1028cd78-a3ee-4236-ab16-9fd7850f90c3",
          "assignee_name": "karthik",
          "subtasks": [
            {
              "id": "QA-5-1",
              "title": "Develop Load Test Scripts",
              "description": "Create scripts to simulate concurrent users.",
              "assignee": "712020:e2598059-441e-4074-80fc-d51b8f3dc5ed",
              "assignee_name": "dhanushya"
            },
            {
              "id": "QA-5-2",
              "title": "Execute Load Tests",
              "description": "Run load tests and analyze results.",
              "assignee": "712020:1028cd78-a3ee-4236-ab16-9fd7850f90c3",
              "assignee_name": "karthik"
            }
          ]
        },
        {
          "id": "PM-3",
          "title": "IT and Security Documentation",
          "description": "As a product manager, I want to ensure all infrastructure and security configurations are documented.",
          "assignee": "712020:06da9bb0-aef1-4524-89c8-418636a8f4cb",
          "assignee_name": "Saran K",
          "subtasks": [
            {
              "id": "PM-3-1",
              "title": "Draft Documentation",
              "description": "Write documentation for infrastructure and security.",
              "assignee": "712020:06da9bb0-aef1-4524-89c8-418636a8f4cb",
              "assignee_name": "Saran K"
            },
            {
              "id": "PM-3-2",
              "title": "Review Documentation",
              "description": "Coordinate review with IT/security teams.",
              "assignee": "712020:d85fee80-33e7-47e6-9060-cf1e53380d45",
              "assignee_name": "satheesh"
            }
          ]
        }
      ]
    }
  ]
}